{
  "entrypoints": {
    "app": {
      "css": [
        "/assets/app.14696144.css"
      ],
      "js": [
        "/assets/app.46186b39.js"
      ]
    },
    "pdf": {
      "js": [
        "/assets/pdf.b806140d.js"
      ]
    },
    "post": {
      "js": [
        "/assets/post.32745565.js"
      ]
    },
    "stream": {
      "js": [
        "/assets/stream.69a126ce.js"
      ]
    },
    "file_manager": {
      "js": [
        "/assets/file_manager.f73924f8.js"
      ]
    },
    "alpine_start": {
      "js": [
        "/assets/alpine_start.c263e8a3.js"
      ]
    },
    "tiptap_basic": {
      "js": [
        "/assets/tiptap_basic.9ffa7a88.js"
      ]
    },
    "studio.posts.editor": {
      "js": [
        "/assets/studio.posts.editor.f917f554.js"
      ]
    },
    "studio.collections": {
      "js": [
        "/assets/studio.collections.01483f3b.js"
      ]
    }
  }
}